{
    "menuSection": "sensors",
    "configItem": [
        {
            "global": 0,
            "name": "MAX6675 Температура",
            "type": "Reading",
            "subtype": "Max6675t",
            "id": "maxtmp",
            "widget": "anydataTmp",
            "page": "Сенсоры",
            "descr": "MAX Температура",
            "int": 15,
            "DO": 12,
            "CS": 13,
            "CLK": 14
        }
    ],
    "about": {
        "authorName": "Serghei Crasnicov",
        "authorContact": "https://t.me/Serghei63",
        "authorGit": "https://github.com/Serghei63",
        "specialThanks": "",
        "moduleName": "Max6675",
        "moduleVersion": "1.0",
        "usedRam": {
            "esp32_4mb": 15,
            "esp8266_4mb": 15
        },
        "title": "Cенсор температуры MAX6675",
        "moduleDesc": "Позволяет получить значения температуры с Max6675 и термопары.",
        "propInfo": {
            "DO": "GPIO шины данных",
            "CS": "GPIO шины данных",
            "CLK": "GPIO шины данных",
            "int": "Количество секунд между опросами датчика."
        }
    },
    "defActive": false,
    "usedLibs": {
        "esp32*": [
            "adafruit/MAX6675 library"
        ],
        "esp82*": [
            "adafruit/MAX6675 library"
        ]
    }
}