{
    "menuSection": "sensors",
    "configItem": [
        {
            "global": 0,
            "name": "SDS011 PM25 Пыль",
            "type": "Reading",
            "subtype": "Sds011_25",
            "id": "pmuart25",
            "widget": "anydataPpm",
            "page": "Сенсоры",
            "descr": "PM-2.5",
            "plus": 0,
            "multiply": 1,
            "round": 10,
            "rxPin": 14,
            "txPin": 16,
            "int": 270,
            "purge": 30,
            "continuousMode": 0,
            "maxRetriesNotAvailable": 100,
            "retryDelayMs": 5
        },
        {
            "global": 0,
            "name": "SDS011 PM10 Пыль",
            "type": "Reading",
            "subtype": "Sds011_10",
            "id": "pmuart10",
            "widget": "anydataPpm",
            "page": "Сенсоры",
            "descr": "PM-10",
            "plus": 0,
            "multiply": 1,
            "round": 10,
            "rxPin": 14,
            "txPin": 16,
            "int": 270,
            "purge": 30,
            "continuousMode": 0,
            "maxRetriesNotAvailable": 100,
            "retryDelayMs": 5
        }
    ],
    "about": {
        "authorName": "Alex K",
        "authorContact": "https://t.me/cmche",
        "authorGit": "https://github.com/CHE77/SDS011forIotManager",
        "specialThanks": "",
        "moduleName": "Sds011",
        "moduleVersion": "2.0 - можно переназначать пины, за один опрос - обновляются два элемента",
        "moduleDesc": "Позволяет получить значения концентрации пыли в воздухе с Sds011.",
        "propInfo": {
            "plus": "поправочный коэффиент +c",
            "multiply": "поправочный коэффиент k*",
            "round": "округление",
            "rxPin": "Esp8266: GPIO 14 - D5, ESP32: GPIO 16 - RX2, > подключаем к TXD сенсора",
            "txPin": "Esp8266: GPIO 16 - D0, ESP32: GPIO 17 - TX2, > подключаем к RXD сенсора",
            "int": "Количество секунд между опросами датчика",
            "purge": "Время продувки сенсора перед замером. Cек.",
            "continuousMode": "1 - Непрерывный режим, 0 - Режим с остановкой (щедящий)",
            "maxRetriesNotAvailable": "Количество попыток ожидания ответа сенсора при опросе (не нужно менять)",
            "retryDelayMs": "Задержка между попытками, миллисекунды (не нужно менять)"
        },
        "title": "Sds011 Датчик концентрации пыли в воздухе"
    },
    "defActive": false,
    "usedLibs": {
        "esp32*": [
            "Nova Fitness Sds dust sensors library@1.5.1"
        ],
        "esp82*": [
            "Nova Fitness Sds dust sensors library@1.5.1"
        ]
    }
}